docs/reference.md
pytest_operator/__init__.py
pytest_operator/plugin.py
pytest_operator/py.typed
pytest_operator/shims.py
pytest_operator-0.43.1.dist-info/licenses/LICENSE
tests/data/build_resources.sh
tests/data/build_resources_errors.sh
tests/data/bundle.yaml
tests/data/etcd_ch_api_response.json
tests/data/model-config.yaml
tests/data/charms/operator-framework/.flake8
tests/data/charms/operator-framework/.jujuignore
tests/data/charms/operator-framework/charmcraft.yaml
tests/data/charms/operator-framework/config.yaml
tests/data/charms/operator-framework/metadata.yaml
tests/data/charms/operator-framework/requirements.txt
tests/data/charms/operator-framework/src/charm.py
tests/data/charms/reactive-framework/config.yaml
tests/data/charms/reactive-framework/layer.yaml
tests/data/charms/reactive-framework/metadata.yaml
tests/data/charms/reactive-framework/wheelhouse.txt
tests/data/charms/reactive-framework/reactive/reactive_framework.py
tests/data/charms/resourced-charm/metadata.yaml
tests/data/test_lib/setup.py
tests/integration/test_add_k8s.py
tests/integration/test_pytest_operator.py
tests/unit/test_pytest_operator.py
pytest_operator-0.43.1.dist-info/METADATA
pytest_operator-0.43.1.dist-info/WHEEL
pytest_operator-0.43.1.dist-info/entry_points.txt
pytest_operator-0.43.1.dist-info/top_level.txt
pytest_operator-0.43.1.dist-info/zip-safe
pytest_operator-0.43.1.dist-info/RECORD
