Metadata-Version: 2.4
Name: pytest-operator
Version: 0.43.1
Summary: Fixtures for Charmed Operators
Author-email: Adam Dyess <adam.dyess@canonical.com>, Mateo Florido <mateo.florido@canonical.com>
License: Apache
Project-URL: Homepage, https://github.com/charmed-kubernetes/pytest-operator
Project-URL: Bug Tracker, https://github.com/charmed-kubernetes/pytest-operator/issues
Keywords: pytest,py.test,operators,ops
Classifier: License :: OSI Approved :: Apache Software License
Classifier: Programming Language :: Python :: 3
Classifier: Programming Language :: Python :: 3.8
Classifier: Programming Language :: Python :: 3.9
Classifier: Programming Language :: Python :: 3.10
Classifier: Programming Language :: Python :: 3.11
Classifier: Programming Language :: Python :: 3.12
Requires-Python: >=3.8
License-File: LICENSE
Requires-Dist: ipdb
Requires-Dist: pytest
Requires-Dist: pytest-asyncio<0.23
Requires-Dist: pyyaml
Requires-Dist: juju
Requires-Dist: jinja2
Dynamic: license-file
